setup.py
WintxREST.egg-info/PKG-INFO
WintxREST.egg-info/SOURCES.txt
WintxREST.egg-info/dependency_links.txt
WintxREST.egg-info/pbr.json
WintxREST.egg-info/requires.txt
WintxREST.egg-info/top_level.txt
wintxrest/__init__.py
wintxrest/default_settings.py
wintxrest/wintxflaskapp.py