Metadata-Version: 1.0
Name: WintxREST
Version: 2.0.0
Summary: A Web API for the Wintx library.
Home-page: UNKNOWN
Author: Seth Cook
Author-email: sethcook@purdue.edu
License: UNKNOWN
Platform: UNKNOWN
Classifier: Development Status :: 5 - Production/Stable
Classifier: Environment :: Web Environment
Classifier: Intended Audience :: Developers
Classifier: Operating System :: Unix
Classifier: Programming Language :: Python :: 2.6
